Metadata-Version: 2.1
Name: linuxmedia-sridhar
Version: 0.1.3
Summary: Linuxmedia is a wrapper for 60 above 60+ Linux Commands
Home-page: https://git.selfmade.ninja/SRIDHARDSCV/packaging_own_cli_tool
Author: Sridhar
Author-email: dcsvsridhar@gmail.com
License: UNKNOWN
Platform: UNKNOWN
Requires-Dist: psutil (==5.9.1)
Requires-Dist: pyspeedtest (==1.2.7)
Requires-Dist: speedtest (==0.0.1)
